{
  "version": "7",
  "dialect": "postgresql",
  "entries": [
    {
      "idx": 0,
      "version": "7",
      "when": 1751310707901,
      "tag": "0000_whole_ego",
      "breakpoints": true
    },
    {
      "idx": 1,
      "version": "7",
      "when": 1751402711965,
      "tag": "0001_secret_sunspot",
      "breakpoints": true
    },
    {
      "idx": 2,
      "version": "7",
      "when": 1751461691361,
      "tag": "0002_steep_prism",
      "breakpoints": true
    },
    {
      "idx": 3,
      "version": "7",
      "when": 1751473782406,
      "tag": "0003_chemical_colonel_america",
      "breakpoints": true
    },
    {
      "idx": 4,
      "version": "7",
      "when": 1751483242586,
      "tag": "0004_remarkable_dragon_lord",
      "breakpoints": true
    }
  ]
}